atomict/__init__.py
atomict/__version__.py
atomict/api.py
atomict/auth.py
atomict/env.py
atomict/exceptions.py
atomict/ase/atatoms.py
atomict/cli/__init__.py
atomict/cli/main.py
atomict/cli/commands/ai_assist.py
atomict/cli/commands/common.py
atomict/cli/commands/convert.py
atomict/cli/commands/helpers.py
atomict/cli/commands/k8s.py
atomict/cli/commands/login.py
atomict/cli/commands/organization.py
atomict/cli/commands/project.py
atomict/cli/commands/task.py
atomict/cli/commands/token.py
atomict/cli/commands/traj.py
atomict/cli/commands/upload.py
atomict/cli/commands/user.py
atomict/cli/commands/workspace.py
atomict/cli/commands/exploration/__init__.py
atomict/cli/commands/exploration/soec.py
atomict/cli/commands/exploration/sqs.py
atomict/cli/commands/simulation/fhiaims.py
atomict/cli/commands/simulation/kpoint.py
atomict/cli/core/client.py
atomict/cli/core/config.py
atomict/cli/core/utils.py
atomict/infra/__init__.py
atomict/infra/logging.py
atomict/infra/distwork/__init__.py
atomict/infra/distwork/environment.py
atomict/infra/distwork/task.py
atomict/io/__init__.py
atomict/io/atoms.py
atomict/io/cif.py
atomict/io/fhiaims.py
atomict/io/trajectory.py
atomict/io/utils.py
atomict/io/formats/__init__.py
atomict/io/formats/atraj.py
atomict/io/formats/tess.py
atomict/io/formats/traj.py
atomict/ml/__init__.py
atomict/ml/model.py
atomict/project/__init__.py
atomict/project/link.py
atomict/project/note.py
atomict/project/project.py
atomict/project/tags.py
atomict/project/workbench.py
atomict/reality/__init__.py
atomict/reality/oqmd.py
atomict/reality/slabs.py
atomict/simulation/__init__.py
atomict/simulation/cantera.py
atomict/simulation/counterfactual.py
atomict/simulation/defect.py
atomict/simulation/ea.py
atomict/simulation/fhi_aims.py
atomict/simulation/impact.py
atomict/simulation/kpoint.py
atomict/simulation/mattergen.py
atomict/simulation/md.py
atomict/simulation/mlrelax.py
atomict/simulation/models.py
atomict/simulation/phonon.py
atomict/simulation/qe.py
atomict-1.2.25.dist-info/licenses/LICENSE
atomict-1.2.25.dist-info/METADATA
atomict-1.2.25.dist-info/WHEEL
atomict-1.2.25.dist-info/entry_points.txt
atomict-1.2.25.dist-info/top_level.txt
atomict-1.2.25.dist-info/RECORD
