Metadata-Version: 2.4
Name: atomict
Version: 1.2.25
Summary: The client application for the https://atomictessellator.com/
Author-email: Steven Anderson <steven@atomictessellator.com>, Alain Richardt <alain@atomictessellator.com>
License: MIT
Project-URL: Homepage, https://github.com/AtomicTessellator/atomic_cli
Keywords: atomic,tessellator,cli,client,fhi-aims,kpoint,sqs
Classifier: Topic :: Scientific/Engineering :: Physics
Classifier: Topic :: Scientific/Engineering :: Artificial Intelligence
Classifier: Topic :: Scientific/Engineering :: Chemistry
Classifier: Intended Audience :: Science/Research
Classifier: Programming Language :: Python :: 3.10
Classifier: Programming Language :: Python :: 3.11
Classifier: Programming Language :: Python :: 3.12
Classifier: Programming Language :: Python :: 3.13
Requires-Python: >=3.10
License-File: LICENSE
Requires-Dist: requests
Requires-Dist: tenacity~=9.0
Requires-Dist: httpx
Requires-Dist: click~=8.0
Requires-Dist: rich~=13.0
Requires-Dist: ase>=3.23.0
Requires-Dist: spglib==2.5.0
Requires-Dist: pymatgen==2025.3.10
Requires-Dist: msgpack==1.1.0
Requires-Dist: msgpack_numpy==0.4.8
Requires-Dist: deepdiff
Requires-Dist: lz4
Provides-Extra: utils
Provides-Extra: dev
Requires-Dist: pytest~=8.0; extra == "dev"
Requires-Dist: black; extra == "dev"
Requires-Dist: isort; extra == "dev"
Requires-Dist: mypy; extra == "dev"
Requires-Dist: flake8; extra == "dev"
Dynamic: license-file
